[
    [
        13,
        "00:12",
        "supplydepot"
    ],
    [
        15,
        "00:35",
        "barracks"
    ],
    [
        17,
        "01:14",
        "commandcenter"
    ],
    [
        19,
        "01:22",
        "marine"
    ],
    [
        19,
        "01:32",
        "orbitalcommand"
    ],
    [
        20,
        "01:40",
        "marine"
    ],
    [
        20,
        "01:41",
        "refinery"
    ],
    [
        21,
        "01:57",
        "mule"
    ],
    [
        21,
        "02:10",
        "commandcenter"
    ],
    [
        22,
        "02:18",
        "refinery"
    ],
    [
        23,
        "02:29",
        "engineeringbay"
    ],
    [
        24,
        "02:32",
        "marine"
    ],
    [
        25,
        "02:43",
        "barracks"
    ],
    [
        26,
        "03:01",
        "mule"
    ],
    [
        26,
        "03:04",
        "planetaryfortress"
    ],
    [
        28,
        "03:04",
        "marine"
    ],
    [
        28,
        "03:05",
        "refinery"
    ],
    [
        28,
        "03:16",
        "barracks"
    ],
    [
        29,
        "03:23",
        "orbitalcommand"
    ],
    [
        31,
        "03:36",
        "marine"
    ],
    [
        31,
        "03:38",
        "factory"
    ],
    [
        32,
        "03:40",
        "marine"
    ],
    [
        34,
        "03:49",
        "mule"
    ],
    [
        36,
        "03:59",
        "factory"
    ],
    [
        37,
        "04:01",
        "marine x 2"
    ],
    [
        38,
        "04:04",
        "mule"
    ],
    [
        39,
        "04:05",
        "marine"
    ],
    [
        43,
        "04:19",
        "barracks"
    ],
    [
        44,
        "04:26",
        "starport"
    ],
    [
        46,
        "04:34",
        "techlab factory"
    ],
    [
        46,
        "04:34",
        "supplydepot"
    ],
    [
        47,
        "04:35",
        "marine x 2"
    ],
    [
        51,
        "04:46",
        "supplydepot"
    ],
    [
        51,
        "04:47",
        "techlab factory"
    ],
    [
        52,
        "04:48",
        "marine"
    ],
    [
        53,
        "04:52",
        "mule"
    ],
    [
        53,
        "04:54",
        "techlab barracks"
    ],
    [
        53,
        "04:54",
        "supplydepot"
    ],
    [
        53,
        "04:55",
        "techlab barracks"
    ],
    [
        56,
        "05:00",
        "siegetank"
    ],
    [
        60,
        "05:05",
        "hellion"
    ],
    [
        61,
        "05:07",
        "mule"
    ],
    [
        62,
        "05:10",
        "marine x 2"
    ],
    [
        63,
        "05:12",
        "supplydepot"
    ],
    [
        67,
        "05:16",
        "liberator"
    ],
    [
        70,
        "05:23",
        "marine"
    ],
    [
        70,
        "05:24",
        "supplydepot"
    ],
    [
        71,
        "05:24",
        "marine"
    ],
    [
        73,
        "05:27",
        "hellion"
    ],
    [
        75,
        "05:29",
        "marine"
    ],
    [
        78,
        "05:35",
        "supplydepot"
    ],
    [
        78,
        "05:35",
        "marine"
    ],
    [
        81,
        "05:38",
        "siegetank"
    ],
    [
        83,
        "05:41",
        "marine x 2"
    ],
    [
        85,
        "05:46",
        "supplydepot"
    ],
    [
        86,
        "05:47",
        "marine"
    ],
    [
        89,
        "05:50",
        "siegetank"
    ],
    [
        90,
        "05:53",
        "marine"
    ],
    [
        91,
        "05:55",
        "mule"
    ],
    [
        91,
        "05:58",
        "supplydepot"
    ],
    [
        92,
        "05:59",
        "marine"
    ],
    [
        92,
        "06:00",
        "techlab starport"
    ],
    [
        93,
        "06:04",
        "marine"
    ],
    [
        94,
        "06:04",
        "barracks"
    ],
    [
        94,
        "06:05",
        "reactor barracks"
    ],
    [
        96,
        "06:10",
        "supplydepot"
    ],
    [
        96,
        "06:11",
        "reactor barracks"
    ],
    [
        96,
        "06:11",
        "mule"
    ],
    [
        96,
        "06:15",
        "missileturret"
    ],
    [
        97,
        "06:16",
        "marine x 2"
    ],
    [
        95,
        "06:22",
        "missileturret"
    ],
    [
        95,
        "06:23",
        "refinery x 2"
    ],
    [
        87,
        "06:26",
        "ghostacademy"
    ],
    [
        85,
        "06:28",
        "missileturret"
    ],
    [
        86,
        "06:34",
        "marine"
    ],
    [
        86,
        "06:35",
        "combatshield"
    ],
    [
        82,
        "06:39",
        "marine x 6"
    ],
    [
        86,
        "06:52",
        "terraninfantryarmorlevel1"
    ],
    [
        87,
        "06:53",
        "marine"
    ],
    [
        87,
        "06:53",
        "commandcenter"
    ],
    [
        89,
        "06:57",
        "barracks"
    ],
    [
        90,
        "07:00",
        "mule"
    ],
    [
        91,
        "07:01",
        "marine x 2"
    ],
    [
        92,
        "07:03",
        "stimpack"
    ],
    [
        93,
        "07:03",
        "marine x 5"
    ],
    [
        100,
        "07:15",
        "mule"
    ],
    [
        102,
        "07:19",
        "marine x 3"
    ],
    [
        105,
        "07:23",
        "commandcenter"
    ],
    [
        104,
        "07:24",
        "marine x 2"
    ],
    [
        105,
        "07:26",
        "supplydepot"
    ],
    [
        108,
        "07:29",
        "liberator"
    ],
    [
        110,
        "07:32",
        "marine"
    ],
    [
        109,
        "07:33",
        "supplydepot"
    ],
    [
        114,
        "07:38",
        "siegetank"
    ],
    [
        115,
        "07:40",
        "marine x 2"
    ],
    [
        120,
        "07:44",
        "siegetank"
    ],
    [
        120,
        "07:45",
        "techlab barracks"
    ],
    [
        121,
        "07:45",
        "marine x 7"
    ],
    [
        130,
        "08:00",
        "barracks"
    ],
    [
        130,
        "08:03",
        "mule"
    ],
    [
        130,
        "08:03",
        "supplydepot"
    ],
    [
        131,
        "08:03",
        "marine"
    ],
    [
        131,
        "08:06",
        "orbitalcommand"
    ],
    [
        131,
        "08:07",
        "refinery x 2"
    ],
    [
        130,
        "08:12",
        "techlab barracks"
    ],
    [
        131,
        "08:13",
        "marine x 3"
    ],
    [
        132,
        "08:15",
        "starport"
    ],
    [
        135,
        "08:17",
        "banshee"
    ],
    [
        135,
        "08:18",
        "mule"
    ],
    [
        135,
        "08:19",
        "bansheecloakingfield"
    ],
    [
        136,
        "08:20",
        "marine x 4"
    ],
    [
        139,
        "08:24",
        "engineeringbay"
    ],
    [
        139,
        "08:29",
        "missileturret"
    ],
    [
        142,
        "08:30",
        "siegetank"
    ],
    [
        143,
        "08:31",
        "marine x 3"
    ],
    [
        145,
        "08:32",
        "mule"
    ],
    [
        146,
        "08:32",
        "marine"
    ],
    [
        143,
        "08:35",
        "refinery"
    ],
    [
        143,
        "08:36",
        "supplydepot"
    ],
    [
        144,
        "08:38",
        "marine x 2"
    ],
    [
        147,
        "08:39",
        "widowmine"
    ],
    [
        147,
        "08:40",
        "refinery"
    ],
    [
        147,
        "08:41",
        "orbitalcommand"
    ],
    [
        149,
        "08:43",
        "ghost"
    ],
    [
        150,
        "08:44",
        "marine"
    ],
    [
        147,
        "08:46",
        "techlab barracks"
    ],
    [
        148,
        "08:49",
        "marine x 2"
    ],
    [
        149,
        "08:50",
        "missileturret"
    ],
    [
        150,
        "08:50",
        "marine x 2"
    ],
    [
        151,
        "08:52",
        "terraninfantryweaponslevel1"
    ],
    [
        151,
        "08:56",
        "marine x 2"
    ],
    [
        152,
        "09:00",
        "armory"
    ],
    [
        153,
        "09:02",
        "marine x 2"
    ],
    [
        158,
        "09:06",
        "mule"
    ],
    [
        158,
        "09:07",
        "supplydepot"
    ],
    [
        160,
        "09:07",
        "marine x 2"
    ],
    [
        161,
        "09:07",
        "mule"
    ],
    [
        162,
        "09:08",
        "marine x 2"
    ],
    [
        163,
        "09:09",
        "personalcloaking"
    ],
    [
        163,
        "09:11",
        "supplydepot"
    ],
    [
        164,
        "09:12",
        "marine x 3"
    ],
    [
        165,
        "09:15",
        "hisecautotracking"
    ],
    [
        165,
        "09:20",
        "marine"
    ],
    [
        168,
        "09:20",
        "banshee"
    ],
    [
        168,
        "09:21",
        "mule"
    ],
    [
        169,
        "09:22",
        "marine x 5"
    ],
    [
        176,
        "09:27",
        "siegetank"
    ],
    [
        176,
        "09:27",
        "supplydepot"
    ],
    [
        177,
        "09:30",
        "marine x 3"
    ],
    [
        182,
        "09:34",
        "siegetank"
    ],
    [
        182,
        "09:35",
        "mule"
    ],
    [
        182,
        "09:35",
        "supplydepot"
    ],
    [
        183,
        "09:38",
        "marine"
    ],
    [
        185,
        "09:38",
        "vikingfighter"
    ],
    [
        184,
        "09:40",
        "marine x 5"
    ],
    [
        190,
        "09:48",
        "marauder"
    ],
    [
        188,
        "09:50",
        "fusioncore"
    ],
    [
        189,
        "09:50",
        "marine"
    ],
    [
        188,
        "09:50",
        "concussiveshells"
    ],
    [
        189,
        "09:51",
        "commandcenter x 2"
    ],
    [
        189,
        "09:51",
        "marine"
    ],
    [
        189,
        "09:51",
        "missileturret"
    ],
    [
        187,
        "09:53",
        "barracks"
    ],
    [
        187,
        "09:56",
        "marine"
    ],
    [
        188,
        "09:58",
        "ghost"
    ],
    [
        187,
        "10:01",
        "marine x 4"
    ],
    [
        195,
        "10:08",
        "thor"
    ],
    [
        196,
        "10:08",
        "marine x 3"
    ],
    [
        197,
        "10:09",
        "mule x 2"
    ],
    [
        198,
        "10:14",
        "marine"
    ],
    [
        196,
        "10:18",
        "terraninfantryarmorlevel2"
    ],
    [
        196,
        "10:18",
        "marine x 4"
    ],
    [
        197,
        "10:25",
        "mule"
    ],
    [
        198,
        "10:26",
        "marine x 5"
    ],
    [
        200,
        "10:36",
        "raven"
    ],
    [
        200,
        "10:38",
        "missileturret"
    ],
    [
        200,
        "10:38",
        "mule"
    ],
    [
        200,
        "10:40",
        "techlab barracks"
    ],
    [
        200,
        "10:40",
        "marine"
    ],
    [
        200,
        "10:42",
        "missileturret"
    ],
    [
        200,
        "10:43",
        "commandcenter"
    ],
    [
        200,
        "10:45",
        "missileturret"
    ],
    [
        200,
        "10:46",
        "commandcenter"
    ],
    [
        200,
        "10:47",
        "terranstructurearmorupgrade"
    ],
    [
        200,
        "10:54",
        "marine x 4"
    ],
    [
        200,
        "11:02",
        "orbitalcommand x 2"
    ],
    [
        199,
        "11:04",
        "refinery"
    ],
    [
        200,
        "11:05",
        "marine x 2"
    ],
    [
        200,
        "11:10",
        "commandcenter"
    ],
    [
        200,
        "11:12",
        "refinery"
    ],
    [
        200,
        "11:12",
        "marine"
    ],
    [
        200,
        "11:14",
        "mule x 2"
    ],
    [
        200,
        "11:14",
        "refinery"
    ]
]